<VAST version="3.0">
    <Ad sequence="1" id="pictxt">
        <InLine>
            <AdSystem>sohu tv ad system</AdSystem>
            <AdTitle>
                <![CDATA[ sohu ]]>
            </AdTitle>
            <Impression id="monitorServer">
                <![CDATA[ http://mmg.aty.sohu.com/pv?type=1&du=1782&al=9479802&vid=4966871&tvid=106352083&rt=1656387269728_840_10.23.253.50_1257381_1257391&spead=0&crid=0&ar=6&plat=3&sver=9.6.30&partner=6932&poid=1&adplat=2&source=1000080005&v1=1048&v1code=101&v2code=101152&prot=json&appid=tv&sdkVersion=13.4.1&offline=0&density=3&displayMetrics=414*736&islocaltv=0&datatype=258&bt=20220628&endtime=20231231&ad=54920&b=417722&bk=115275976&pagetype=1&islocaltv=0&guid=2d8af0f88f4a4278956be9eba1188e9b&adpr=0&seq=1&w=644&h=322&wdbn=644&hgbn=322&cheattype=16&sperotime=1656387269&template=pictxt&platsource=tv&indexip=adveng-retrvl-qa.adveng.svc.cluster.local:60111&vu=0&vc=101141;101147;101152&ispgc=0&impressionid=68ff047c93b438c6b48c3edfd2dce857&scope=0&flightid=36582216&from=tvssp&advertiserid=11635&encd=ydpcJ8ELpl0HEGSYmapTQ5Ro9gX8%2FpXAKDRru1wY0xakxASnOmGQrxJPdnWNlrOmk6%2BMDlyoy1urZUtitYn4PKQB96OPwt%2FgzwkRXZ5bxX1CRUn27OWrZ5PC0izVIu7hEWN28K%2F6rf7zM%2BKngNeZkL%2F9EPYh6X%2Ff9G7RuGxXxnmb2GqeyQ9%2BFAgRQnCCRJjejKJqzTjnUZTgmnC1ino6TiNs%2BVr53ysH7ICGk0rkvBknWufYqrQoooFC15JxEGmq0kZWWzjTW87Q3O4F0mT7Fy1utMZ6FjQarCMM13S%2BVcoSibZo5OOF1B%2FS4RTEgMNO8u8pw68x0y9hO41XM%2B4VKwqU0FmoUUxp0B1LWqDO5ZS%2FFSi6ULXDej7vmgst5q07hpHPS0JOUNr6m3oNENebWg9r%2FALpQvOzzSY1RVzk3vV8EZMyKN8cnWx3%2F1GPg%2FtsbOqjpdDduShLPvxdBZTDJjznswiQRh%2FKX9xVWaIzNLiaeKomjERBjHMLWyMHgnnutPl3CSTnZ8U%3D&vp=s&at=0&c=1&v1=1048&p=15512&loc=Unknown&adstyle=15512&ac=5480&ad=54920&pt=12613&b=417722&bk=115275976&pagetype=1&spead=0&rtm=__TIME__&err=[ERRORCODE] ]]>
            </Impression>
            <Impression id="sohutv" offset="">
                <![CDATA[ http://mmg.aty.sohu.com/pvlog?du=1782&al=9479802&vid=4966871&tvid=106352083&rt=1656387269728_840_10.23.253.50_1257381_1257391&spead=0&crid=0&ar=6&plat=3&sver=9.6.30&partner=6932&poid=1&adplat=2&source=1000080005&v1=1048&v1code=101&v2code=101152&prot=json&appid=tv&sdkVersion=13.4.1&offline=0&density=3&displayMetrics=414*736&islocaltv=0&datatype=258&bt=20220628&endtime=20231231&ad=54920&b=417722&bk=115275976&pagetype=1&islocaltv=0&guid=2d8af0f88f4a4278956be9eba1188e9b&adpr=0&seq=1&w=644&h=322&wdbn=644&hgbn=322&cheattype=16&sperotime=1656387269&template=pictxt&platsource=tv&indexip=adveng-retrvl-qa.adveng.svc.cluster.local:60111&vu=0&vc=101141;101147;101152&ispgc=0&impressionid=68ff047c93b438c6b48c3edfd2dce857&scope=0&flightid=36582216&from=tvssp&advertiserid=11635&encd=ydpcJ8ELpl0HEGSYmapTQ5Ro9gX8%2FpXAKDRru1wY0xakxASnOmGQrxJPdnWNlrOmk6%2BMDlyoy1urZUtitYn4PKQB96OPwt%2FgzwkRXZ5bxX1CRUn27OWrZ5PC0izVIu7hEWN28K%2F6rf7zM%2BKngNeZkL%2F9EPYh6X%2Ff9G7RuGxXxnmb2GqeyQ9%2BFAgRQnCCRJjejKJqzTjnUZTgmnC1ino6TiNs%2BVr53ysH7ICGk0rkvBknWufYqrQoooFC15JxEGmq0kZWWzjTW87Q3O4F0mT7Fy1utMZ6FjQarCMM13S%2BVcoSibZo5OOF1B%2FS4RTEgMNO8u8pw68x0y9hO41XM%2B4VKwqU0FmoUUxp0B1LWqDO5ZS%2FFSi6ULXDej7vmgst5q07hpHPS0JOUNr6m3oNENebWg9r%2FALpQvOzzSY1RVzk3vV8EZMyKN8cnWx3%2F1GPg%2FtsbOqjpdDduShLPvxdBZTDJjznswiQRh%2FKX9xVWaIzNLiaeKomjERBjHMLWyMHgnnutPl3CSTnZ8U%3D&vp=0&at=0&c=1&v1=1048&p=15512&loc=Unknown&adstyle=15512&ac=5480&ad=54920&pt=12613&b=417722&bk=115275976&pagetype=1&spead=0&rtm=__TIME__ ]]>
            </Impression>
            <Creatives>
                <Creative>
                    <CompanionAds>
                        <Companion width="644" height="322">
                            <StaticResource creativeType="image/jpeg">
                                <![CDATA[ https://images.sohu.com/ytv/SH/11642/644322202001141355341.jpg ]]>
                            </StaticResource>
                            <CompanionClickThrough>
                                <![CDATA[ http://www.baidu.com ]]>
                            </CompanionClickThrough>
                            <MultiClickTracking>
                                <![CDATA[ http://mmg.aty.sohu.com/goto?du=1782&al=9479802&vid=4966871&tvid=106352083&rt=1656387269728_840_10.23.253.50_1257381_1257391&spead=0&crid=0&ar=6&plat=3&sver=9.6.30&partner=6932&poid=1&adplat=2&source=1000080005&v1=1048&v1code=101&v2code=101152&prot=json&appid=tv&sdkVersion=13.4.1&offline=0&density=3&displayMetrics=414*736&datatype=258&bt=20220628&endtime=20231231&ad=54920&b=417722&bk=115275976&pagetype=1&islocaltv=0&guid=2d8af0f88f4a4278956be9eba1188e9b&adpr=0&seq=1&w=644&h=322&wdbn=644&hgbn=322&cheattype=16&sperotime=1656387269&template=pictxt&platsource=tv&indexip=adveng-retrvl-qa.adveng.svc.cluster.local:60111&vu=0&vc=101141;101147;101152&ispgc=0&impressionid=68ff047c93b438c6b48c3edfd2dce857&scope=0&flightid=36582216&from=tvssp&advertiserid=11635&encd=ydpcJ8ELpl0HEGSYmapTQ5Ro9gX8%2FpXAKDRru1wY0xakxASnOmGQrxJPdnWNlrOmk6%2BMDlyoy1urZUtitYn4PKQB96OPwt%2FgzwkRXZ5bxX1CRUn27OWrZ5PC0izVIu7hEWN28K%2F6rf7zM%2BKngNeZkL%2F9EPYh6X%2Ff9G7RuGxXxnmb2GqeyQ9%2BFAgRQnCCRJjejKJqzTjnUZTgmnC1ino6TiNs%2BVr53ysH7ICGk0rkvBknWufYqrQoooFC15JxEGmq0kZWWzjTW87Q3O4F0mT7Fy1utMZ6FjQarCMM13S%2BVcoSibZo5OOF1B%2FS4RTEgMNO8u8pw68x0y9hO41XM%2B4VKwqU0FmoUUxp0B1LWqDO5ZS%2FFSi6ULXDej7vmgst5q07hpHPS0JOUNr6m3oNENebWg9r%2FALpQvOzzSY1RVzk3vV8EZMyKN8cnWx3%2F1GPg%2FtsbOqjpdDduShLPvxdBZTDJjznswiQRh%2FKX9xVWaIzNLiaeKomjERBjHMLWyMHgnnutPl3CSTnZ8U%3D&err=[ERRORCODE]&at=0&c=1&v1=1048&p=15512&loc=Unknown&adstyle=15512&ac=5480&ad=54920&pt=12613&b=417722&bk=115275976&pagetype=1&spead=0&eventtype=deeplink ]]>
                            </MultiClickTracking>
                            <CompanionClickTracking>
                                <![CDATA[ http://mmg.aty.sohu.com/goto?du=1782&al=9479802&vid=4966871&tvid=106352083&rt=1656387269728_840_10.23.253.50_1257381_1257391&spead=0&crid=0&ar=6&plat=3&sver=9.6.30&partner=6932&poid=1&adplat=2&source=1000080005&v1=1048&v1code=101&v2code=101152&prot=json&appid=tv&sdkVersion=13.4.1&offline=0&density=3&displayMetrics=414*736&datatype=258&bt=20220628&endtime=20231231&ad=54920&b=417722&bk=115275976&pagetype=1&islocaltv=0&guid=2d8af0f88f4a4278956be9eba1188e9b&adpr=0&seq=1&w=644&h=322&wdbn=644&hgbn=322&cheattype=16&sperotime=1656387269&template=pictxt&platsource=tv&indexip=adveng-retrvl-qa.adveng.svc.cluster.local:60111&vu=0&vc=101141;101147;101152&ispgc=0&impressionid=68ff047c93b438c6b48c3edfd2dce857&scope=0&flightid=36582216&from=tvssp&advertiserid=11635&encd=ydpcJ8ELpl0HEGSYmapTQ5Ro9gX8%2FpXAKDRru1wY0xakxASnOmGQrxJPdnWNlrOmk6%2BMDlyoy1urZUtitYn4PKQB96OPwt%2FgzwkRXZ5bxX1CRUn27OWrZ5PC0izVIu7hEWN28K%2F6rf7zM%2BKngNeZkL%2F9EPYh6X%2Ff9G7RuGxXxnmb2GqeyQ9%2BFAgRQnCCRJjejKJqzTjnUZTgmnC1ino6TiNs%2BVr53ysH7ICGk0rkvBknWufYqrQoooFC15JxEGmq0kZWWzjTW87Q3O4F0mT7Fy1utMZ6FjQarCMM13S%2BVcoSibZo5OOF1B%2FS4RTEgMNO8u8pw68x0y9hO41XM%2B4VKwqU0FmoUUxp0B1LWqDO5ZS%2FFSi6ULXDej7vmgst5q07hpHPS0JOUNr6m3oNENebWg9r%2FALpQvOzzSY1RVzk3vV8EZMyKN8cnWx3%2F1GPg%2FtsbOqjpdDduShLPvxdBZTDJjznswiQRh%2FKX9xVWaIzNLiaeKomjERBjHMLWyMHgnnutPl3CSTnZ8U%3D&err=[ERRORCODE]&at=0&c=1&v1=1048&p=15512&loc=Unknown&adstyle=15512&ac=5480&ad=54920&pt=12613&b=417722&bk=115275976&pagetype=1&spead=0&rtm=__TIME__ ]]>
                            </CompanionClickTracking>
                            <TrackingEvents>
                                <Tracking event="av">
                                    <![CDATA[ http://mmg.aty.sohu.com/av?type=1&du=1782&al=9479802&vid=4966871&tvid=106352083&rt=1656387269728_840_10.23.253.50_1257381_1257391&spead=0&crid=0&ar=6&plat=3&sver=9.6.30&partner=6932&poid=1&adplat=2&source=1000080005&v1=1048&v1code=101&v2code=101152&prot=json&appid=tv&sdkVersion=13.4.1&offline=0&density=3&displayMetrics=414*736&islocaltv=0&datatype=258&bt=20220628&endtime=20231231&ad=54920&b=417722&bk=115275976&pagetype=1&islocaltv=0&guid=2d8af0f88f4a4278956be9eba1188e9b&adpr=0&seq=1&w=644&h=322&wdbn=644&hgbn=322&cheattype=16&sperotime=1656387269&template=pictxt&platsource=tv&indexip=adveng-retrvl-qa.adveng.svc.cluster.local:60111&vu=0&vc=101141;101147;101152&ispgc=0&impressionid=68ff047c93b438c6b48c3edfd2dce857&scope=0&flightid=36582216&from=tvssp&advertiserid=11635&encd=ydpcJ8ELpl0HEGSYmapTQ5Ro9gX8%2FpXAKDRru1wY0xakxASnOmGQrxJPdnWNlrOmk6%2BMDlyoy1urZUtitYn4PKQB96OPwt%2FgzwkRXZ5bxX1CRUn27OWrZ5PC0izVIu7hEWN28K%2F6rf7zM%2BKngNeZkL%2F9EPYh6X%2Ff9G7RuGxXxnmb2GqeyQ9%2BFAgRQnCCRJjejKJqzTjnUZTgmnC1ino6TiNs%2BVr53ysH7ICGk0rkvBknWufYqrQoooFC15JxEGmq0kZWWzjTW87Q3O4F0mT7Fy1utMZ6FjQarCMM13S%2BVcoSibZo5OOF1B%2FS4RTEgMNO8u8pw68x0y9hO41XM%2B4VKwqU0FmoUUxp0B1LWqDO5ZS%2FFSi6ULXDej7vmgst5q07hpHPS0JOUNr6m3oNENebWg9r%2FALpQvOzzSY1RVzk3vV8EZMyKN8cnWx3%2F1GPg%2FtsbOqjpdDduShLPvxdBZTDJjznswiQRh%2FKX9xVWaIzNLiaeKomjERBjHMLWyMHgnnutPl3CSTnZ8U%3D&vp=s&at=0&c=1&v1=1048&p=15512&loc=Unknown&adstyle=15512&ac=5480&ad=54920&pt=12613&b=417722&bk=115275976&pagetype=1 ]]>
                                </Tracking>
                                <Tracking event="close">
                                    <![CDATA[ http://mmg.aty.sohu.com/pvlog?du=1782&al=9479802&vid=4966871&tvid=106352083&rt=1656387269728_840_10.23.253.50_1257381_1257391&spead=0&crid=0&ar=6&plat=3&sver=9.6.30&partner=6932&poid=1&adplat=2&source=1000080005&v1=1048&v1code=101&v2code=101152&prot=json&appid=tv&sdkVersion=13.4.1&offline=0&density=3&displayMetrics=414*736&islocaltv=0&datatype=258&bt=20220628&endtime=20231231&ad=54920&b=417722&bk=115275976&pagetype=1&islocaltv=0&guid=2d8af0f88f4a4278956be9eba1188e9b&adpr=0&seq=1&w=644&h=322&wdbn=644&hgbn=322&cheattype=16&sperotime=1656387269&template=pictxt&platsource=tv&indexip=adveng-retrvl-qa.adveng.svc.cluster.local:60111&vu=0&vc=101141;101147;101152&ispgc=0&impressionid=68ff047c93b438c6b48c3edfd2dce857&scope=0&flightid=36582216&from=tvssp&advertiserid=11635&encd=ydpcJ8ELpl0HEGSYmapTQ5Ro9gX8%2FpXAKDRru1wY0xakxASnOmGQrxJPdnWNlrOmk6%2BMDlyoy1urZUtitYn4PKQB96OPwt%2FgzwkRXZ5bxX1CRUn27OWrZ5PC0izVIu7hEWN28K%2F6rf7zM%2BKngNeZkL%2F9EPYh6X%2Ff9G7RuGxXxnmb2GqeyQ9%2BFAgRQnCCRJjejKJqzTjnUZTgmnC1ino6TiNs%2BVr53ysH7ICGk0rkvBknWufYqrQoooFC15JxEGmq0kZWWzjTW87Q3O4F0mT7Fy1utMZ6FjQarCMM13S%2BVcoSibZo5OOF1B%2FS4RTEgMNO8u8pw68x0y9hO41XM%2B4VKwqU0FmoUUxp0B1LWqDO5ZS%2FFSi6ULXDej7vmgst5q07hpHPS0JOUNr6m3oNENebWg9r%2FALpQvOzzSY1RVzk3vV8EZMyKN8cnWx3%2F1GPg%2FtsbOqjpdDduShLPvxdBZTDJjznswiQRh%2FKX9xVWaIzNLiaeKomjERBjHMLWyMHgnnutPl3CSTnZ8U%3D?&err=[ERRORCODE]&at=0&c=1&v1=1048&p=15512&loc=Unknown&adstyle=15512&ac=5480&ad=54920&pt=12613&b=417722&bk=115275976&pagetype=1&spead=0&eventtype=feedback&feedbackreason=__FEEDBACKCODE__ ]]>
                                </Tracking>
                            </TrackingEvents>
                        </Companion>
                    </CompanionAds>
                </Creative>
            </Creatives>
            <Extensions>
                <Extension>
                    <Resource>ssp</Resource>
                    <AdParams adStyle="0" postCode="15512"/>
                    <Position>0</Position>
                    <Advertiser>
                        <![CDATA[ ]]>
                    </Advertiser>
                    <Status>1</Status>
                    <SupportDeepLink>0</SupportDeepLink>
                    <Hardflag>0</Hardflag>
                    <Excluded>0</Excluded>
                    <SupportUnion>1</SupportUnion>
                </Extension>
            </Extensions>
        </InLine>
    </Ad>
    <Ad sequence="2" id="gallerypicdownload">
        <InLine>
            <AdSystem>sohu tv ad system</AdSystem>
            <AdTitle>sohu tv</AdTitle>
            <Description>sohu tv</Description>
            <Impression id="monitorServer">
                <![CDATA[ http://mmg.aty.sohu.com/pvlog?vp=s&c=1&v1=1048&p=14369&loc=Unknown&adstyle=14369&du=1782&al=9479802&vid=4966871&tvid=106352083&rt=1656387269728_840_10.23.253.50_1257381_1257391&crid=0&ar=6&plat=3&sver=9.6.30&partner=6932&poid=1&adplat=2&source=1000080005&v1=1048&v1code=101&v2code=101152&prot=json&appid=tv&sdkVersion=13.4.1&offline=0&density=3&displayMetrics=414*736&islocaltv=0&datatype=258&bt=20220628&pagetype=1&islocaltv=0&guid=2d8af0f88f4a4278956be9eba1188e9b&adpr=0&seq=2&w=644&h=322&wdbn=644&hgbn=322&cheattype=16&sperotime=1656387269&platsource=tv&indexip=adveng-retrvl-qa.adveng.svc.cluster.local:60111&vu=0&vc=101141;101147;101152&ispgc=0&impressionid=68ff047c93b438c6b48c3edfd2dce857&scope=0&from=tvssp&encd=ydpcJ8ELpl0HEGSYmapTQ5Ro9gX8%2FpXAKDRru1wY0xakxASnOmGQrxJPdnWNlrOmk6%2BMDlyoy1urZUtitYn4PKQB96OPwt%2FgzwkRXZ5bxX1CRUn27OWrZ5PC0izVIu7hEWN28K%2F6rf7zM%2BKngNeZkL%2F9EPYh6X%2Ff9G7RuGxXxnmb2GqeyQ9%2BFAgRQnCCRJjejKJqzTjnUZTgmnC1ino6TiNs%2BVr53ysH7ICGk0rkvBknWufYqrQoooFC15JxEGmq0kZWWzjTW87Q3O4F0mT7Fy1utMZ6FjQarCMM13S%2BVcoSibZo5OOF1B%2FS4RTEgMNO8u8pw68x0y9hO41XM%2B4VKwqU0FmoUUxp0B1LWqDO5ZS%2FFSi6ULXDej7vmgst5q07hpHPS0JOUNr6m3oNENebWg9r%2FALpQvOzzSY1RVzk3vV8EZMyKN8cnWx3%2F1GPg%2FtsbOqjpdDduShLPvxdBZTDJjznswiQRh%2FKX9xVWaIzNLiaeKomjERBjHMLWyMHgnnutPl3CSTnZ8U%3D&sspreplacable=1&sspreqid=ssp-app-qa-77997689cc-95wtm0000001262ba76c6021e_cl ]]>
            </Impression>
            <Creatives>
                <Creative>
                    <CompanionAds more="http://hui.sohu.com/test/prj/brand/">
                        <Companion width="692" height="191">
                            <StaticResource creativeType="image/jpeg">
                                <![CDATA[ ]]>
                            </StaticResource>
                            <AltText>
                                <![CDATA[ ]]>
                            </AltText>
                            <TrackingEvents/>
                        </Companion>
                    </CompanionAds>
                </Creative>
            </Creatives>
            <Extensions>
                <Extension>
                    <Resource>ssp</Resource>
                    <AdParams adStyle="1" postCode="14369"/>
                    <Position>0</Position>
                    <Status>0</Status>
                    <SupportUnion>1</SupportUnion>
                </Extension>
            </Extensions>
        </InLine>
    </Ad>
</VAST>